is_star/__init__.py
is_star/main.py
is_star-0.0.3.dist-info/METADATA
is_star-0.0.3.dist-info/WHEEL
is_star-0.0.3.dist-info/top_level.txt
is_star-0.0.3.dist-info/RECORD
